textureminer/__init__.py
textureminer/__main__.py
textureminer/cli.py
textureminer/exceptions.py
textureminer/file.py
textureminer/logger.py
textureminer/options.py
textureminer/py.typed
textureminer/texts.py
textureminer/edition/Bedrock.py
textureminer/edition/Edition.py
textureminer/edition/Java.py
textureminer/edition/__init__.py
textureminer-4.1.0.dist-info/METADATA
textureminer-4.1.0.dist-info/WHEEL
textureminer-4.1.0.dist-info/entry_points.txt
textureminer-4.1.0.dist-info/licenses/LICENSE
textureminer-4.1.0.dist-info/RECORD
