Metadata-Version: 2.3
Name: textureminer
Version: 4.1.0
Summary: Library and CLI program to extract and scale Minecraft item and block textures.
Project-URL: Home, https://github.com/4mbl/textureminer
Project-URL: Bug Tracker, https://github.com/4mbl/textureminer/issues
Project-URL: Changelog, https://github.com/4mbl/textureminer/blob/main/CHANGELOG.md
Project-URL: Documentation, https://github.com/4mbl/textureminer/blob/main/README.md
Project-URL: Repository, https://github.com/4mbl/textureminer
Author: 4MBL
License: MIT License
License-File: LICENSE
Keywords: cli,minecraft
Classifier: Development Status :: 5 - Production/Stable
Classifier: Environment :: Console
Classifier: Intended Audience :: Developers
Classifier: License :: OSI Approved :: MIT License
Classifier: Natural Language :: English
Classifier: Operating System :: OS Independent
Classifier: Programming Language :: Python :: 3
Classifier: Programming Language :: Python :: 3.12
Classifier: Programming Language :: Python :: 3.13
Classifier: Programming Language :: Python :: Implementation :: CPython
Classifier: Topic :: Software Development
Classifier: Topic :: Software Development :: Libraries
Classifier: Topic :: Utilities
Classifier: Typing :: Typed
Requires-Python: >=3.12
Requires-Dist: forfiles<5.1.0,>=5.0.0
Requires-Dist: fortext<1.1.0,>=1.0.0
Requires-Dist: pillow<11.1.0,>=11.0.0
Requires-Dist: requests<2.33.0,>=2.32.0
